imgmasks/__init__.py
imgmasks/annulus.py
imgmasks/circle.py
imgmasks/ellipse.py
imgmasks-1.0.dist-info/LICENSE.txt
imgmasks-1.0.dist-info/METADATA
imgmasks-1.0.dist-info/WHEEL
imgmasks-1.0.dist-info/top_level.txt
imgmasks-1.0.dist-info/RECORD
