Metadata-Version: 2.1
Name: imgmasks
Version: 1.0
Summary: makes arbitrary elliptical, circular, and annular binary masks for image processing
Home-page: https://github.com/briley-lewis/elliptical-mask
Author: UNKNOWN
Author-email: UNKNOWN
License: MIT
Platform: UNKNOWN
Requires-Dist: numpy
Requires-Dist: matplotlib
